{"credit":"Tom","parent":"custom/blocks/hanger","parent":"custom/block-parent","textures":{"3":"custom/blocks/clothing"},"elements":[{"from":[1.73556,0.98901,7.00045],"to":[14.23556,14.98901,9.00045],"rotation":{"angle":0,"axis":"y","origin":[8,23.5,8]},"faces":{"north":{"uv":[5.625,5.125,7.25,6.875],"texture":"#3","tintindex":0},"east":{"uv":[6.875,5.125,7.125,6.875],"texture":"#3","tintindex":0},"south":{"uv":[5.625,5.125,7.25,6.875],"texture":"#3","tintindex":0},"west":{"uv":[6.875,5.125,7.125,6.875],"texture":"#3","tintindex":0},"up":{"uv":[5.625,5.125,7.25,5.25],"texture":"#3","tintindex":0},"down":{"uv":[7.5,9.875,5.375,10.125],"texture":"#3","tintindex":0}}},{"from":[14.23556,0.98901,7.00045],"to":[1.73556,14.98901,9.00045],"rotation":{"angle":0,"axis":"y","origin":[8,23.5,8]},"faces":{"north":{"uv":[5.625,5.125,7.25,6.875],"texture":"#3","tintindex":0},"east":{"uv":[6.875,5.125,7.125,6.875],"texture":"#3","tintindex":0},"south":{"uv":[5.625,5.125,7.25,6.875],"texture":"#3","tintindex":0},"west":{"uv":[6.875,5.125,7.125,6.875],"texture":"#3","tintindex":0},"up":{"uv":[5.375,3.625,7.5,3.75],"texture":"#3","tintindex":0},"down":{"uv":[7.5,9.875,5.375,10.125],"texture":"#3","tintindex":0}}},{"from":[2.73556,14.98901,7.00045],"to":[13.23556,27.23901,9.00045],"rotation":{"angle":0,"axis":"y","origin":[8,23.5,8]},"faces":{"north":{"uv":[5.75,3.625,7.125,5.125],"texture":"#3","tintindex":0},"east":{"uv":[5.75,3.625,6,5.125],"texture":"#3","tintindex":0},"south":{"uv":[5.75,3.625,7.125,5.125],"texture":"#3","tintindex":0},"west":{"uv":[5.75,3.625,6,5.125],"texture":"#3","tintindex":0},"up":{"uv":[5.75,3.625,7.125,3.75],"texture":"#3","tintindex":0},"down":{"uv":[7.5,9.875,5.375,10.125],"texture":"#3","tintindex":0}}},{"from":[-0.26444,24.23901,8.00045],"to":[16.23556,31.23901,8.00045],"rotation":{"angle":0,"axis":"y","origin":[8,23.5,8]},"faces":{"north":{"uv":[7.25,0.25,5.125,1.125],"texture":"#3"},"east":{"uv":[0,0,0,0.875],"texture":"#3"},"south":{"uv":[5.125,0.25,7.25,1.125],"texture":"#3"},"west":{"uv":[0,0,0,0.875],"texture":"#3"},"up":{"uv":[2.125,0,0,0],"texture":"#3"},"down":{"uv":[2.125,0,0,0],"texture":"#3"}}}],"display":{"head":{"translation":[0,-30.25,0],"scale":[1.6,1.6,1.6]}},"groups":[0,1,2,{"name":"group","origin":[8,23.75,8],"color":0,"children":[3]}]}