{"texture_size":[64,64],"textures":{"1":"custom/entity/rocket_race/projectile/projectile-chunk"},"elements":[{"from":[4,0,4.25],"to":[12,8,14.25],"rotation":{"angle":0,"axis":"y","origin":[4,0,4.25]},"faces":{"north":{"uv":[2.5,5,4.5,7],"texture":"#1"},"east":{"uv":[0,0,2.5,2],"texture":"#1"},"south":{"uv":[0,5.75,2,7.75],"texture":"#1"},"west":{"uv":[0,2,2.5,4],"texture":"#1"},"up":{"uv":[4.5,2.5,2.5,0],"texture":"#1"},"down":{"uv":[4.5,2.5,2.5,5],"texture":"#1"}}},{"from":[12,4,4.25],"to":[18,4,14.25],"rotation":{"angle":0,"axis":"y","origin":[4,0,4.25]},"faces":{"north":{"uv":[0,0,1.5,0],"texture":"#1","tintindex":0},"east":{"uv":[0,0,2.5,0],"texture":"#1","tintindex":0},"south":{"uv":[0,0,1.5,0],"texture":"#1","tintindex":0},"west":{"uv":[0,0,2.5,0],"texture":"#1","tintindex":0},"up":{"uv":[6,9.25,4.5,6.75],"texture":"#1","tintindex":0},"down":{"uv":[3.5,9.5,2,7],"rotation":180,"texture":"#1","tintindex":0}}},{"from":[-2,4,4.25],"to":[4,4,14.25],"rotation":{"angle":0,"axis":"y","origin":[12,0,4.25]},"faces":{"north":{"uv":[0,0,1.5,0],"texture":"#1","tintindex":0},"east":{"uv":[0,0,2.5,0],"texture":"#1","tintindex":0},"south":{"uv":[0,0,1.5,0],"texture":"#1","tintindex":0},"west":{"uv":[0,0,2.5,0],"texture":"#1","tintindex":0},"up":{"uv":[3.5,9.5,2,7],"texture":"#1","tintindex":0},"down":{"uv":[6,9.25,4.5,6.75],"rotation":180,"texture":"#1","tintindex":0}}},{"from":[8,8,4.25],"to":[8,14,14.25],"rotation":{"angle":0,"axis":"z","origin":[8,4,9.25]},"faces":{"north":{"uv":[0,0,0,1.5],"texture":"#1","tintindex":0},"east":{"uv":[7.75,3,10.25,4.5],"texture":"#1","tintindex":0},"south":{"uv":[0,0,0,1.5],"texture":"#1","tintindex":0},"west":{"uv":[7.75,4.5,10.25,6],"texture":"#1","tintindex":0},"up":{"uv":[0,2.5,0,0],"texture":"#1","tintindex":0},"down":{"uv":[0,0,0,2.5],"texture":"#1","tintindex":0}}},{"from":[8,-6,4.25],"to":[8,0,14.25],"rotation":{"angle":0,"axis":"z","origin":[8,12,9.25]},"faces":{"north":{"uv":[0,1.5,0,0],"texture":"#1","tintindex":0},"east":{"uv":[7.75,4.5,10.25,3],"texture":"#1","tintindex":0},"south":{"uv":[0,1.5,0,0],"texture":"#1","tintindex":0},"west":{"uv":[7.75,6,10.25,4.5],"texture":"#1","tintindex":0},"up":{"uv":[0,2.5,0,0],"texture":"#1","tintindex":0},"down":{"uv":[0,0,0,2.5],"texture":"#1","tintindex":0}}},{"from":[5,1,0.25],"to":[11,7,4.25],"rotation":{"angle":0,"axis":"y","origin":[4,0,4.25]},"faces":{"north":{"uv":[9,7.5,10.5,9],"texture":"#1","tintindex":0},"east":{"uv":[3.5,7,4.5,8.5],"texture":"#1","tintindex":0},"south":{"uv":[9,9,10.5,10.5],"texture":"#1","tintindex":0},"west":{"uv":[3.5,8.5,4.5,10],"texture":"#1","tintindex":0},"up":{"uv":[1.5,10.25,0,9.25],"texture":"#1","tintindex":0},"down":{"uv":[6,9.25,4.5,10.25],"texture":"#1","tintindex":0}}},{"from":[3,4,-2.75],"to":[13,4,4.25],"rotation":{"angle":-45,"axis":"z","origin":[8,4,2.25]},"faces":{"north":{"uv":[0,0,2.5,0],"texture":"#1","tintindex":0},"east":{"uv":[0,0,1.75,0],"texture":"#1","tintindex":0},"south":{"uv":[0,0,2.5,0],"texture":"#1","tintindex":0},"west":{"uv":[0,0,1.75,0],"texture":"#1","tintindex":0},"up":{"uv":[2.5,5.75,0,4],"texture":"#1","tintindex":0},"down":{"uv":[7,0,4.5,1.75],"texture":"#1","tintindex":0}}},{"from":[8,-1,-2.75],"to":[8,9,4.25],"rotation":{"angle":-45,"axis":"z","origin":[8,4,2.25]},"faces":{"north":{"uv":[0,0,0,2.5],"texture":"#1","tintindex":0},"east":{"uv":[4.5,1.75,6.25,4.25],"texture":"#1","tintindex":0},"south":{"uv":[0,0,0,2.5],"texture":"#1","tintindex":0},"west":{"uv":[4.5,4.25,6.25,6.75],"texture":"#1","tintindex":0},"up":{"uv":[0,1.75,0,0],"texture":"#1","tintindex":0},"down":{"uv":[0,0,0,1.75],"texture":"#1","tintindex":0}}},{"from":[5,1,14.25],"to":[11,7,16.25],"rotation":{"angle":45,"axis":"z","origin":[8,4,15.25]},"faces":{"north":{"uv":[0,7.75,1.5,9.25],"texture":"#1","tintindex":0},"east":{"uv":[1.5,7.75,2,9.25],"texture":"#1","tintindex":0},"south":{"uv":[9,6,10.5,7.5],"texture":"#1","tintindex":0},"west":{"uv":[1.5,9.25,2,10.75],"texture":"#1","tintindex":0},"up":{"uv":[7.5,9.75,6,9.25],"texture":"#1","tintindex":0},"down":{"uv":[9,9.25,7.5,9.75],"texture":"#1","tintindex":0}}}],"display":{"head":{"rotation":[90,0,0],"translation":[0,-3.25,10],"scale":[2.50781,2.50781,2.50781]}}}