{"texture_size":[128,128],"textures":{"0":"custom/gui/buttons/rocket_race/crafting","particle":"custom/gui/buttons/rocket_race/crafting"},"elements":[{"from":[-1,-1,1],"to":[17,17,1],"rotation":{"angle":0,"axis":"y","origin":[-1,-1,0]},"faces":{"north":{"uv":[2.375,0,4.625,2.25],"texture":"#0"},"east":{"uv":[2.375,0,4.625,2.25],"texture":"#0"},"south":{"uv":[2.375,0,4.625,2.25],"texture":"#0"},"west":{"uv":[2.375,0,4.625,2.25],"texture":"#0"},"up":{"uv":[2.375,0,4.625,2.25],"texture":"#0"},"down":{"uv":[2.375,0,4.625,2.25],"texture":"#0"}}}],"gui_light":"front","display":{}}